id3manager/__init__.py
id3manager/__main__.py
id3manager/metadata.py
id3manager/utils.py
id3manager/formats/__init__.py
id3manager/formats/abc.py
id3manager/formats/formats.py
id3manager/formats/text.py
id3manager/formats/toml.py
id3manager-0.2.0.dist-info/METADATA
id3manager-0.2.0.dist-info/WHEEL
id3manager-0.2.0.dist-info/entry_points.txt
id3manager-0.2.0.dist-info/licenses/LICENSE
id3manager-0.2.0.dist-info/RECORD
