Metadata-Version: 2.4
Name: id3manager
Version: 0.2.0
Summary: The ID3 metadata manager for MP3 files.
Project-URL: Documentation, https://github.com/ikalnytskyi/id3manager#readme
Project-URL: Issues, https://github.com/ikalnytskyi/id3manager/issues
Project-URL: Source, https://github.com/ikalnytskyi/id3manager
Author-email: Ihor Kalnytskyi <ihor@kalnytskyi.com>
License-Expression: MIT
License-File: LICENSE
Keywords: audio,id3,metadata,mp3,tags
Classifier: Development Status :: 4 - Beta
Classifier: Programming Language :: Python
Classifier: Programming Language :: Python :: 3.9
Classifier: Programming Language :: Python :: 3.10
Classifier: Programming Language :: Python :: 3.11
Classifier: Programming Language :: Python :: 3.12
Classifier: Programming Language :: Python :: 3.13
Classifier: Programming Language :: Python :: Implementation :: CPython
Classifier: Programming Language :: Python :: Implementation :: PyPy
Requires-Python: >=3.9
Requires-Dist: mutagen>=1.46.0
Requires-Dist: tomlkit>=0.11.6
